pipecat_ai_bey-0.0.3.dist-info/licenses/LICENSE
pipecat_bey/transport.py
pipecat_ai_bey-0.0.3.dist-info/METADATA
pipecat_ai_bey-0.0.3.dist-info/WHEEL
pipecat_ai_bey-0.0.3.dist-info/top_level.txt
pipecat_ai_bey-0.0.3.dist-info/RECORD
