Metadata-Version: 2.4
Name: pipecat-ai-bey
Version: 0.0.3
Summary: Generate real-time video avatars for your Pipecat AI agents with Beyond Presence
License-Expression: BSD-2-Clause
Project-URL: Source, https://github.com/bey-dev/pipecat-bey
Project-URL: Website, https://beyondpresence.ai
Keywords: webrtc,audio,video,ai
Classifier: Development Status :: 5 - Production/Stable
Classifier: Intended Audience :: Developers
Classifier: Topic :: Communications :: Conferencing
Classifier: Topic :: Multimedia :: Sound/Audio
Classifier: Topic :: Multimedia :: Video
Classifier: Topic :: Scientific/Engineering :: Artificial Intelligence
Requires-Python: >=3.10
License-File: LICENSE
Requires-Dist: pipecat-ai[daily]==0.0.89
Dynamic: license-file
